nakdimon_ort/__init__.py
nakdimon_ort/config.json
nakdimon_ort/config.py
nakdimon_ort/model.py
nakdimon_ort-0.1.5.dist-info/WHEEL
nakdimon_ort-0.1.5.dist-info/METADATA
nakdimon_ort-0.1.5.dist-info/RECORD
