Metadata-Version: 2.1
Name: nakdimon-ort
Version: 0.1.5
Summary: Hebrew diacritics in onnxruntime
Author: thewh1teagle
Requires-Dist: onnxruntime>=1.0
Requires-Dist: twine ; extra == "build"
Requires-Dist: build ; extra == "build"
Requires-Dist: tox ; extra == "dev"
Requires-Dist: pre-commit ; extra == "dev"
Requires-Dist: bump2version ; extra == "dev"
Requires-Dist: pytest ; extra == "test"
Project-URL: home, https://github.com/thewh1teagle/nakdimon-ort
Provides-Extra: build
Provides-Extra: dev
Provides-Extra: test
